hmi/__init__.py
hmi/hmi.py
hmi/main.py
hmi/metadata.py
hmi-0.1.dist-info/LICENSE
hmi-0.1.dist-info/METADATA
hmi-0.1.dist-info/WHEEL
hmi-0.1.dist-info/top_level.txt
hmi-0.1.dist-info/RECORD
