Metadata-Version: 2.1
Name: hmi
Version: 0.1
Summary: The ``hmi`` package is a python module that provides an interface to compute distances between locations based on [Özak's (2018, ](http://rdcu.be/I4YI)[2010)](http://omerozak.com/pdf/Ozak_voyage.pdf) [Human Mobility Index](https://human-mobility-index.github.io/).
Author-email: Ömer Özak <omer@omerozak.com>
Project-URL: Homepage, https://github.com/human-mobility-index/hmi
Project-URL: Issues, https://github.com/human-mobility-index/hmi/issues
Classifier: Programming Language :: Python :: 3
Classifier: Operating System :: OS Independent
Classifier: Development Status :: 3 - Alpha
Classifier: Topic :: Utilities
Classifier: License :: OSI Approved :: GNU General Public License v3 or later (GPLv3+)
Classifier: Intended Audience :: Developers
Classifier: Intended Audience :: Science/Research
Classifier: Operating System :: OS Independent
Classifier: Programming Language :: Python
Classifier: Topic :: Scientific/Engineering :: GIS
Classifier: Programming Language :: Python :: 2
Classifier: Programming Language :: Python :: 2.7
Classifier: Programming Language :: Python :: 3
Classifier: Programming Language :: Python :: 3.4
Classifier: Programming Language :: Python :: 3.5
Classifier: Programming Language :: Python :: 3.6
Classifier: Programming Language :: Python :: 3.7
Classifier: Programming Language :: Python :: 3.8
Classifier: Programming Language :: Python :: 3.9
Classifier: Programming Language :: Python :: 3.10
Classifier: Programming Language :: Python :: 3.11
Classifier: Programming Language :: Python :: 3.12
Requires-Python: >=3.8
License-File: LICENSE
